cldr/__init__.py
cldr/_cli.py
cldr/py.typed
cldr-0.2.0.dist-info/METADATA
cldr-0.2.0.dist-info/WHEEL
cldr-0.2.0.dist-info/entry_points.txt
cldr-0.2.0.dist-info/top_level.txt
cldr-0.2.0.dist-info/RECORD
