Metadata-Version: 2.1
Name: cldr
Version: 0.2.0
Summary: ChangeLog Driven Releases (CLDR)...
Home-page: https://github.com/bbugyi200/cldr
Author: Bryan M Bugyi
Author-email: bryanbugyi34@gmail.com
License: MIT license
Platform: UNKNOWN
Classifier: Development Status :: 3 - Alpha
Classifier: Intended Audience :: Developers
Classifier: License :: OSI Approved :: MIT License
Classifier: Natural Language :: English
Classifier: Programming Language :: Python :: 3
Classifier: Programming Language :: Python :: 3.8
Classifier: Programming Language :: Python :: 3.9
Classifier: Programming Language :: Python :: 3.10
Requires-Python: >=3.8
Requires-Dist: pydantic
Requires-Dist: pylogutils
Requires-Dist: python-clap
